src/__init__.py
src/aidd/__init__.py
src/aidd/cli.py
src/aidd/server.py
src/aidd/tools/__init__.py
src/aidd/tools/base.py
src/aidd/tools/code_analysis.py
src/aidd/tools/code_execution.py
src/aidd/tools/code_tools.py
src/aidd/tools/directory_tools.py
src/aidd/tools/file_tools.py
src/aidd/tools/get_active_apps_tool.py
src/aidd/tools/get_available_windows_tool.py
src/aidd/tools/image_tools.py
src/aidd/tools/other_tools.py
src/aidd/tools/path_tools.py
src/aidd/tools/screenshot_tool.py
src/aidd/tools/state.py
src/aidd/tools/system_tools.py
src/aidd/tools/todo_store.py
src/aidd/tools/todo_tools.py
src/aidd/tools/web_tools.py
skydeckai_code_fastmcp-0.1.42.dist-info/METADATA
skydeckai_code_fastmcp-0.1.42.dist-info/WHEEL
skydeckai_code_fastmcp-0.1.42.dist-info/entry_points.txt
skydeckai_code_fastmcp-0.1.42.dist-info/licenses/LICENSE
skydeckai_code_fastmcp-0.1.42.dist-info/RECORD
